pip_brief/__init__.py
pip_brief/cli.py
pip_brief/core.py
pip_brief-1.0.0.dist-info/licenses/LICENSE
pip_brief-1.0.0.dist-info/METADATA
pip_brief-1.0.0.dist-info/WHEEL
pip_brief-1.0.0.dist-info/entry_points.txt
pip_brief-1.0.0.dist-info/top_level.txt
pip_brief-1.0.0.dist-info/RECORD
