Metadata-Version: 2.4
Name: pip-brief
Version: 1.0.0
Summary: A simple wrapper for pip install with clean, organized output
Author-email: Nachiket Mehendale <your-email@example.com>
License: MIT License
Project-URL: Homepage, https://github.com/Nachiket-Mehendale/pip-brief
Project-URL: Repository, https://github.com/Nachiket-Mehendale/pip-brief
Project-URL: Issues, https://github.com/Nachiket-Mehendale/pip-brief/issues
Keywords: pip,wrapper,cli,package-manager,install,summary
Classifier: Development Status :: 5 - Production/Stable
Classifier: Intended Audience :: Developers
Classifier: License :: OSI Approved :: MIT License
Classifier: Operating System :: OS Independent
Classifier: Programming Language :: Python :: 3
Classifier: Programming Language :: Python :: 3.6
Classifier: Programming Language :: Python :: 3.7
Classifier: Programming Language :: Python :: 3.8
Classifier: Programming Language :: Python :: 3.9
Classifier: Programming Language :: Python :: 3.10
Classifier: Programming Language :: Python :: 3.11
Classifier: Programming Language :: Python :: 3.12
Classifier: Programming Language :: Python :: 3.13
Classifier: Topic :: Software Development :: Libraries :: Python Modules
Classifier: Topic :: System :: Installation/Setup
Classifier: Topic :: Utilities
Requires-Python: >=3.6
License-File: LICENSE
Dynamic: license-file
